omnisafe/__init__.py
omnisafe/evaluator.py
omnisafe/typing.py
omnisafe/version.py
omnisafe/adapter/__init__.py
omnisafe/adapter/early_terminated_adapter.py
omnisafe/adapter/modelbased_adapter.py
omnisafe/adapter/offline_adapter.py
omnisafe/adapter/offpolicy_adapter.py
omnisafe/adapter/online_adapter.py
omnisafe/adapter/onpolicy_adapter.py
omnisafe/adapter/saute_adapter.py
omnisafe/adapter/simmer_adapter.py
omnisafe/algorithms/__init__.py
omnisafe/algorithms/algo_wrapper.py
omnisafe/algorithms/base_algo.py
omnisafe/algorithms/registry.py
omnisafe/algorithms/model_based/__init__.py
omnisafe/algorithms/model_based/cap_pets.py
omnisafe/algorithms/model_based/cce_pets.py
omnisafe/algorithms/model_based/rce_pets.py
omnisafe/algorithms/model_based/safeloop.py
omnisafe/algorithms/model_based/base/__init__.py
omnisafe/algorithms/model_based/base/ensemble.py
omnisafe/algorithms/model_based/base/loop.py
omnisafe/algorithms/model_based/base/pets.py
omnisafe/algorithms/model_based/planner/__init__.py
omnisafe/algorithms/model_based/planner/arc.py
omnisafe/algorithms/model_based/planner/cap.py
omnisafe/algorithms/model_based/planner/cce.py
omnisafe/algorithms/model_based/planner/cem.py
omnisafe/algorithms/model_based/planner/rce.py
omnisafe/algorithms/model_based/planner/safe_arc.py
omnisafe/algorithms/off_policy/__init__.py
omnisafe/algorithms/off_policy/ddpg.py
omnisafe/algorithms/off_policy/ddpg_lag.py
omnisafe/algorithms/off_policy/ddpg_pid.py
omnisafe/algorithms/off_policy/sac.py
omnisafe/algorithms/off_policy/sac_lag.py
omnisafe/algorithms/off_policy/sac_pid.py
omnisafe/algorithms/off_policy/td3.py
omnisafe/algorithms/off_policy/td3_lag.py
omnisafe/algorithms/off_policy/td3_pid.py
omnisafe/algorithms/offline/__init__.py
omnisafe/algorithms/offline/base.py
omnisafe/algorithms/offline/bcq.py
omnisafe/algorithms/offline/bcq_lag.py
omnisafe/algorithms/offline/c_crr.py
omnisafe/algorithms/offline/coptidice.py
omnisafe/algorithms/offline/crr.py
omnisafe-0.5.0.dist-info/LICENSE
omnisafe-0.5.0.dist-info/METADATA
omnisafe-0.5.0.dist-info/WHEEL
omnisafe-0.5.0.dist-info/entry_points.txt
omnisafe-0.5.0.dist-info/top_level.txt
omnisafe-0.5.0.dist-info/RECORD
