Metadata-Version: 2.1
Name: omnisafe
Version: 0.5.0
Summary: A comprehensive and reliable benchmark for safe reinforcement learning.
Author: OmniSafe Contributors
License: Apache License, Version 2.0
Project-URL: Homepage, https://github.com/PKU-Alignment/omnisafe
Project-URL: Repository, https://github.com/PKU-Alignment/omnisafe
Project-URL: Documentation, https://omnisafe.readthedocs.io
Project-URL: Bug Report, https://github.com/PKU-Alignment/omnisafe/issues
Keywords: Safe Reinforcement Learning,Reinforcement Learning,PyTorch
Classifier: Development Status :: 4 - Beta
Classifier: License :: OSI Approved :: Apache Software License
Classifier: Programming Language :: Python :: 3
Classifier: Programming Language :: Python :: 3.8
Classifier: Programming Language :: Python :: 3.9
Classifier: Programming Language :: Python :: 3.10
Classifier: Programming Language :: Python :: 3.11
Classifier: Intended Audience :: Science/Research
Classifier: Topic :: Scientific/Engineering :: Artificial Intelligence
Classifier: Topic :: Software Development :: Libraries :: Python Modules
Requires-Python: >=3.8
License-File: LICENSE
Requires-Dist: safety-gymnasium >=0.2.0
Requires-Dist: torch >=1.10.0
Requires-Dist: numpy >=1.20.0
Requires-Dist: tensorboard >=2.8.0
Requires-Dist: wandb >=0.13.0
Requires-Dist: pyyaml >=6.0
Requires-Dist: moviepy >=1.0.0
Requires-Dist: typing-extensions >=4.0.0
Requires-Dist: typer[all] >=0.7.0
Requires-Dist: seaborn >=0.12.2
Requires-Dist: pandas ==2.0.3
Requires-Dist: matplotlib >=3.7.1
Requires-Dist: gdown >=4.6.0
Provides-Extra: lint
Requires-Dist: isort >=5.11.0 ; extra == 'lint'
Requires-Dist: black >=22.6.0 ; extra == 'lint'
Requires-Dist: pylint[spelling] >=2.15.0 ; extra == 'lint'
Requires-Dist: mypy >=0.990 ; extra == 'lint'
Requires-Dist: flake8 ; extra == 'lint'
Requires-Dist: flake8-bugbear ; extra == 'lint'
Requires-Dist: ruff ; extra == 'lint'
Requires-Dist: doc8 ; extra == 'lint'
Requires-Dist: pydocstyle ; extra == 'lint'
Requires-Dist: pyenchant ; extra == 'lint'
Requires-Dist: pre-commit ; extra == 'lint'
Provides-Extra: test
Requires-Dist: pytest ; extra == 'test'
Requires-Dist: pytest-cov ; extra == 'test'
Requires-Dist: pytest-xdist ; extra == 'test'
